github_release_downloader/__init__.py
github_release_downloader/__main__.py
github_release_downloader/_meta.py
github_release_downloader/core.py
github_release_downloader/data.py
github_release_downloader/models.py
github_release_downloader-1.1.0.dist-info/LICENSE.md
github_release_downloader-1.1.0.dist-info/METADATA
github_release_downloader-1.1.0.dist-info/WHEEL
github_release_downloader-1.1.0.dist-info/top_level.txt
github_release_downloader-1.1.0.dist-info/RECORD
