Metadata-Version: 2.1
Name: github_release_downloader
Version: 1.1.0
Summary: Package to download any release assets from the latest compatible version
Author: MaxBQb
License: MIT license
Project-URL: Homepage, https://github.com/MBQbUtils/GithubReleaseDownloader
Project-URL: Bug Tracker, https://github.com/MBQbUtils/GithubReleaseDownloader/issues
Keywords: github,release,download,asset,downloader
Classifier: Programming Language :: Python :: 3
Classifier: Programming Language :: Python :: 3.7
Classifier: Programming Language :: Python :: 3.8
Classifier: Programming Language :: Python :: 3.9
Classifier: Programming Language :: Python :: 3.10
Classifier: Programming Language :: Python :: 3.11
Classifier: Intended Audience :: Developers
Classifier: Natural Language :: English
Classifier: Programming Language :: Python :: Implementation :: CPython
Classifier: Topic :: Software Development :: Libraries :: Python Modules
Requires-Python: >=3.7
License-File: LICENSE.md
